decoratemethod.py
decoratemethod-0.1.1.dist-info/LICENSE
decoratemethod-0.1.1.dist-info/WHEEL
decoratemethod-0.1.1.dist-info/METADATA
decoratemethod-0.1.1.dist-info/RECORD
