Metadata-Version: 2.1
Name: decoratemethod
Version: 0.1.1
Summary: Let function decorator decorate the bound method of per instance.
Home-page: https://github.com/Cologler/decoratemethod-python
License: MIT
Author: Cologler
Author-email: skyoflw@gmail.com
Requires-Python: >=3.8,<4.0
Classifier: License :: OSI Approved :: MIT License
Classifier: Programming Language :: Python :: 3
Classifier: Programming Language :: Python :: 3.8
Classifier: Programming Language :: Python :: 3.9
Project-URL: Repository, https://github.com/Cologler/decoratemethod-python
